applications/__init__.py
applications/root_finder.py
pyautodiff/__init__.py
pyautodiff/ops.py
pyautodiff/trig_ops.py
pyautodiff/var.py
pyautodiff/visualization.py
4dpyautodiff-1.0.0.dist-info/METADATA
4dpyautodiff-1.0.0.dist-info/WHEEL
4dpyautodiff-1.0.0.dist-info/top_level.txt
4dpyautodiff-1.0.0.dist-info/RECORD
