Metadata-Version: 2.1
Name: 4dpyautodiff
Version: 1.0.0
Summary: A simple library for auto differentiation
Home-page: https://github.com/cs107-JTGC/cs107-FinalProject
Author: cs107-JTGC
Author-email: chenfanzhuang@g.harvard.edu
License: MIT
Platform: UNKNOWN
Classifier: Programming Language :: Python :: 3
Classifier: License :: OSI Approved :: MIT License
Classifier: Operating System :: OS Independent
Requires-Python: >=3.6
Requires-Dist: numpy
Requires-Dist: graphviz
